README.md
setup.py
cella/__init__.py
cella.egg-info/PKG-INFO
cella.egg-info/SOURCES.txt
cella.egg-info/dependency_links.txt
cella.egg-info/not-zip-safe
cella.egg-info/requires.txt
cella.egg-info/top_level.txt