Metadata-Version: 1.1
Name: cella
Version: 0.0.1
Summary: Cella
Home-page: https://github.com/amrali/cella
Author: Amr Ali, Saad Talaat
Author-email: amralicc@gmail.com, saadtalaat@gmail.com
License: UNKNOWN
Platform: POSIX
Classifier: License :: OSI Approved :: Mozilla Public License 2.0 (MPL 2.0)
Classifier: Operating System :: OS Independent
Classifier: Programming Language :: Python :: 3 :: Only
Classifier: Natural Language :: English
Classifier: Intended Audience :: Developers
Classifier: Topic :: Software Development :: Libraries :: Application Frameworks
